vumit/__init__.py
vumit/ai_service.py
vumit/cli.py
vumit/git_analyzer.py
vumit-1.0.0.dist-info/METADATA
vumit-1.0.0.dist-info/WHEEL
vumit-1.0.0.dist-info/entry_points.txt
vumit-1.0.0.dist-info/licenses/LICENSE
vumit-1.0.0.dist-info/RECORD
