Metadata-Version: 2.4
Name: vumit
Version: 1.0.0
Summary: AI-powered Git analysis tool using Gemini AI
Project-URL: Documentation, https://github.com/vumit/vumit#readme
Project-URL: Issues, https://github.com/vumit/vumit/issues
Author: Vumit Contributors
License: MIT License
License-File: LICENSE
Keywords: ai,code-review,git,merge-request
Classifier: Development Status :: 4 - Beta
Classifier: Environment :: Console
Classifier: Intended Audience :: Developers
Classifier: License :: OSI Approved :: MIT License
Classifier: Programming Language :: Python :: 3.9
Classifier: Topic :: Software Development :: Version Control :: Git
Requires-Python: >=3.9
Requires-Dist: click>=8.1.8
Requires-Dist: gitpython>=3.1.44
Requires-Dist: google-generativeai>=0.8.4
Requires-Dist: hatchling>=1.27.0
Requires-Dist: rich>=13.9.4
